synth_sdk/__init__.py
synth_sdk/config/__init__.py
synth_sdk/config/settings.py
synth_sdk/provider_support/__init__.py
synth_sdk/provider_support/anthropic.py
synth_sdk/provider_support/openai.py
synth_sdk/provider_support/suppress_logging.py
synth_sdk/tracing/__init__.py
synth_sdk/tracing/abstractions.py
synth_sdk/tracing/base_client.py
synth_sdk/tracing/client_manager.py
synth_sdk/tracing/config.py
synth_sdk/tracing/context.py
synth_sdk/tracing/decorators.py
synth_sdk/tracing/immediate_client.py
synth_sdk/tracing/local.py
synth_sdk/tracing/log_client_base.py
synth_sdk/tracing/retry_queue.py
synth_sdk/tracing/trackers.py
synth_sdk/tracing/upload.py
synth_sdk/tracing/utils.py
synth_sdk/tracing/events/__init__.py
synth_sdk/tracing/events/manage.py
synth_sdk/tracing/events/scope.py
synth_sdk/tracing/events/store.py
tutorials/__init__.py
tutorials/async_agent_example.py
tutorials/simple_agent_example.py
synth_sdk-0.3.0.dist-info/METADATA
synth_sdk-0.3.0.dist-info/WHEEL
synth_sdk-0.3.0.dist-info/top_level.txt
synth_sdk-0.3.0.dist-info/RECORD
