Metadata-Version: 2.2
Name: synth-sdk
Version: 0.3.0
Author: Synth AI
Author-email: Synth AI <josh@usesynth.ai>
License: MIT
Project-URL: Homepage, https://github.com/synth-laboratories/synth-sdk
Requires-Python: >=3.10
Requires-Dist: opentelemetry-api
Requires-Dist: opentelemetry-sdk
Requires-Dist: pydantic
Requires-Dist: requests
Requires-Dist: asyncio
Requires-Dist: build>=1.2.2.post1
Requires-Dist: pypi
Requires-Dist: twine>=4.0.0
Requires-Dist: keyring>=24.0.0
Requires-Dist: python-dotenv>=1.0.1
Requires-Dist: langfuse>=2.53.9
Requires-Dist: pytest>=8.3.3
Requires-Dist: pydantic-openapi-schema>=1.5.1
Requires-Dist: pytest-asyncio>=0.24.0
Requires-Dist: boto3>=1.35.71
Requires-Dist: botocore>=1.35.71
Requires-Dist: tqdm>=4.66.4
Dynamic: author
Dynamic: requires-python
